Metadata-Version: 2.1
Name: wedpr-authenticator
Version: 3.0.0.post20241124
Summary: WeDPR Authenticator: Authenticate JupyterHub users with wedpr providers
Home-page: https://jupyter.org
Author: WeDPR Team
Author-email: jupyter@googlegroups.com
License: BSD
Keywords: Interactive,Interpreter,Shell,Web
Platform: Linux
Platform: Mac OS X
Platform: Windows
Classifier: Intended Audience :: Developers
Classifier: Intended Audience :: System Administrators
Classifier: Intended Audience :: Science/Research
Classifier: Programming Language :: Python
Classifier: Programming Language :: Python :: 3
Requires-Python: >=3.8
Requires-Dist: traitlets>=4.3.2
Requires-Dist: jupyter_server>=2.2
Requires-Dist: pyjwt>=2
Requires-Dist: tornado
